tightwrap/__init__.py
tightwrap/_backported.py
tightwrap/py.typed
tightwrap-24.3.0.dist-info/METADATA
tightwrap-24.3.0.dist-info/WHEEL
tightwrap-24.3.0.dist-info/licenses/LICENSE
tightwrap-24.3.0.dist-info/RECORD
